jobbergate_agent/__init__.py
jobbergate_agent/clients/__init__.py
jobbergate_agent/clients/cluster_api.py
jobbergate_agent/clients/influx.py
jobbergate_agent/internals/__init__.py
jobbergate_agent/internals/update.py
jobbergate_agent/jobbergate/__init__.py
jobbergate_agent/jobbergate/constants.py
jobbergate_agent/jobbergate/pagination.py
jobbergate_agent/jobbergate/report_health.py
jobbergate_agent/jobbergate/schemas.py
jobbergate_agent/jobbergate/submit.py
jobbergate_agent/jobbergate/update.py
jobbergate_agent/main.py
jobbergate_agent/settings.py
jobbergate_agent/tasks.py
jobbergate_agent/utils/__init__.py
jobbergate_agent/utils/compute.py
jobbergate_agent/utils/exception.py
jobbergate_agent/utils/logging.py
jobbergate_agent/utils/plugin.py
jobbergate_agent/utils/scheduler.py
jobbergate_agent/utils/sentry.py
jobbergate_agent/utils/user_mapper.py
jobbergate_agent-5.9.0.dist-info/LICENSE
jobbergate_agent-5.9.0.dist-info/METADATA
jobbergate_agent-5.9.0.dist-info/WHEEL
jobbergate_agent-5.9.0.dist-info/entry_points.txt
jobbergate_agent-5.9.0.dist-info/RECORD
