Metadata-Version: 2.1
Name: jobbergate-agent
Version: 5.9.0
Summary: Jobbergate Agent
Home-page: https://github.com/omnivector-solutions/jobbergate
License: MIT
Author: Omnivector Solutions
Author-email: info@omnivector.solutions
Requires-Python: >=3.10,<4.0
Classifier: Development Status :: 5 - Production/Stable
Classifier: License :: OSI Approved :: MIT License
Classifier: Operating System :: OS Independent
Classifier: Programming Language :: Python :: 3
Classifier: Programming Language :: Python :: 3.10
Classifier: Programming Language :: Python :: 3.11
Classifier: Topic :: Scientific/Engineering
Requires-Dist: apscheduler (==3.10.3)
Requires-Dist: auto-name-enum (>=3.0.0,<4.0.0)
Requires-Dist: influxdb (>=5.3.2,<6.0.0)
Requires-Dist: jobbergate-core (==5.9.0)
Requires-Dist: msgpack (>=1.1.2,<2.0.0)
Requires-Dist: numba (>=0.63.1,<0.64.0)
Requires-Dist: pluggy (>=1.6.0,<2.0.0)
Requires-Dist: pydantic-settings (>=2.12.0,<3.0.0)
Requires-Dist: python-dotenv (>=1.2.1,<2.0.0)
Requires-Dist: sentry-sdk (>=2.47.0,<3.0.0)
Project-URL: Bug Tracker, https://github.com/omnivector-solutions/jobbergate/issues
Project-URL: Changelog, https://github.com/omnivector-solutions/jobbergate/blob/main/jobbergate-agent/CHANGELOG.rst
Project-URL: Repository, https://github.com/omnivector-solutions/jobbergate
